[{"address1": "338 Pitt Street", "address2": "Level 8", "city": "Sydney", "state": "NSW", "zip": "2000", "country": "Australia", "website": "https://www.bigtincan.com", "industry": "Software - Application", "industryKey": "software-application", "industryDisp": "Software - Application", "sector": "Technology", "sectorKey": "technology", "sectorDisp": "Technology", "longBusinessSummary": "Bigtincan Holdings Limited operates as a sales enablement automation company. The company's platforms includes Bigtincan Hub, a powerful, intelligent, collaborative, and secure solution that automatically delivers relevant content to the right users directly, using their mobile devices. It offers engagement platform solutions, which combines content, communication, and interaction insights; security solutions for the secure distribution and management of documents and other media content. The company's solutions are used for sales, marketing, and channel partners. It serves life sciences, financial, retail, technology, manufacturing, telecommunication, and energy industries, as well as governments. The company was founded in 2010 and is headquartered in Sydney, Australia.", "companyOfficers": [{"maxAge": 1, "name": "Mr. David  Keane", "title": "Co-Founder, CEO & Executive Director", "fiscalYear": 2023, "totalPay": 354823, "exercisedValue": 0, "unexercisedValue": 0}, {"maxAge": 1, "name": "Mr. Patrick  Welch", "title": "President & Chief Marketing Officer", "fiscalYear": 2023, "exercisedValue": 0, "unexercisedValue": 0}, {"maxAge": 1, "name": "Cyril  Desouza", "title": "Global Finance Manager", "fiscalYear": 2023, "exercisedValue": 0, "unexercisedValue": 0}, {"maxAge": 1, "name": "Mr. Vivian  Stewart", "age": 51, "title": "Chief Operating Officer", "yearBorn": 1972, "fiscalYear": 2023, "exercisedValue": 0, "unexercisedValue": 0}, {"maxAge": 1, "name": "Mr. Kent  Erickson", "title": "Senior Vice President of Product Management", "fiscalYear": 2023, "exercisedValue": 0, "unexercisedValue": 0}, {"maxAge": 1, "name": "Mike  Maggio", "title": "Head of European Operations", "fiscalYear": 2023, "exercisedValue": 0, "unexercisedValue": 0}, {"maxAge": 1, "name": "Mr. Stefan  Teulon", "title": "Chief Product Officer", "fiscalYear": 2023, "exercisedValue": 0, "unexercisedValue": 0}, {"maxAge": 1, "name": "Ms. Debra Bond Cancro", "title": "Head of Voice Analytics", "fiscalYear": 2023, "exercisedValue": 0, "unexercisedValue": 0}, {"maxAge": 1, "name": "Ms. Lucy  Rowe", "age": 46, "title": "Company Secretary", "yearBorn": 1977, "fiscalYear": 2023, "exercisedValue": 0, "unexercisedValue": 0}, {"maxAge": 1, "name": "Ms. Tara  Garnett", "title": "Senior Product Manager", "fiscalYear": 2023, "exercisedValue": 0, "unexercisedValue": 0}], "compensationAsOfEpochDate": 1703980800, "maxAge": 86400, "priceHint": 4, "previousClose": 0.108, "open": 0.108, "dayLow": 0.108, "dayHigh": 0.108, "regularMarketPreviousClose": 0.108, "regularMarketOpen": 0.108, "regularMarketDayLow": 0.108, "regularMarketDayHigh": 0.108, "beta": 1.146, "volume": 100216, "regularMarketVolume": 100216, "averageVolume": 18449, "averageVolume10days": 402, "averageDailyVolume10Day": 402, "marketCap": 172190896, "fiftyTwoWeekLow": 0.03, "fiftyTwoWeekHigh": 0.39, "priceToSalesTrailing12Months": 1.417244, "fiftyDayAverage": 0.099018, "twoHundredDayAverage": 0.1439585, "currency": "USD", "enterpriseValue": 234916800, "profitMargins": -0.16388, "floatShares": 448131230, "sharesOutstanding": 716598016, "heldPercentInsiders": 0.05198, "heldPercentInstitutions": 0.31328, "impliedSharesOutstanding": 1594360064, "bookValue": 0.355, "priceToBook": 0.30422536, "lastFiscalYearEnd": 1688083200, "nextFiscalYearEnd": 1719705600, "mostRecentQuarter": 1703980800, "netIncomeToCommon": -19911000, "trailingEps": -0.02, "enterpriseToRevenue": 1.934, "enterpriseToEbitda": -30.087, "52WeekChange": -0.9230769, "SandP52WeekChange": 0.2586832, "exchange": "PNK", "quoteType": "EQUITY", "symbol": "BTGHF", "underlyingSymbol": "BTGHF", "shortName": "BIGTINCAN HOLDINGS LTD", "longName": "Bigtincan Holdings Limited", "firstTradeDateEpochUtc": 1580740200, "timeZoneFullName": "America/New_York", "timeZoneShortName": "EDT", "uuid": "a9a97c10-b906-33f8-b1e7-bc576f4a6a29", "messageBoardId": "finmb_419757196", "gmtOffSetMilliseconds": -14400000, "currentPrice": 0.108, "recommendationKey": "none", "totalCash": 19477000, "totalCashPerShare": 0.032, "ebitda": -7807847, "totalDebt": 15563000, "quickRatio": 0.521, "currentRatio": 0.631, "totalRevenue": 121497000, "debtToEquity": 7.248, "revenuePerShare": 0.201, "returnOnAssets": -0.041729998, "returnOnEquity": -0.08895001, "freeCashflow": 2914846, "operatingCashflow": -15789000, "revenueGrowth": -0.015, "grossMargins": 0.87996, "ebitdaMargins": -0.06426, "operatingMargins": -0.13402, "financialCurrency": "AUD", "trailingPegRatio": null, "__fetch_time": "2024-06-21"}]