[{"address1": "GrandyVic Building", "address2": "21st Floor Taiyanggong Middle Road Chaoyang District", "city": "Beijing", "zip": "100028", "country": "China", "phone": "86 10 8462 8340", "website": "https://ir.zhipin.com", "industry": "Internet Content & Information", "industryKey": "internet-content-information", "industryDisp": "Internet Content & Information", "sector": "Communication Services", "sectorKey": "communication-services", "sectorDisp": "Communication Services", "longBusinessSummary": "Kanzhun Limited, together with its subsidiaries, operates an online recruitment platform in the People's Republic of China. It offers job seeking services that allow job seekers to receive job recommendations, initiate direct chats, and deliver resumes upon mutual consent, as well as value-added tools. The company also provides direct recruitment services to enterprise users to post jobs, receive personalized candidate recommendations, engage in direct communication, and receive resumes upon mutual consent. In addition, it offers online recruitment services through BOSS Zhipin, a mobile app; and management consultancy and technical services. Kanzhun Limited was founded in 2013 and is headquartered in Beijing, the People's Republic of China.", "fullTimeEmployees": 4884, "companyOfficers": [{"maxAge": 1, "name": "Mr. Peng  Zhao", "age": 53, "title": "Founder, Chairman & CEO", "yearBorn": 1972, "fiscalYear": 2024, "totalPay": 1026746, "exercisedValue": 0, "unexercisedValue": 0}, {"maxAge": 1, "name": "Mr. Xu  Chen", "age": 48, "title": "President & Executive Director", "yearBorn": 1977, "fiscalYear": 2024, "totalPay": 746618, "exercisedValue": 0, "unexercisedValue": 0}, {"maxAge": 1, "name": "Mr. Tao  Zhang", "age": 42, "title": "CTO & Executive Director", "yearBorn": 1983, "fiscalYear": 2024, "totalPay": 715901, "exercisedValue": 0, "unexercisedValue": 0}, {"maxAge": 1, "name": "Mr. Yu  Zhang", "age": 47, "title": "Chief Strategy Officer", "yearBorn": 1978, "fiscalYear": 2024, "totalPay": 731921, "exercisedValue": 0, "unexercisedValue": 0}, {"maxAge": 1, "name": "Ms. Xiehua  Wang", "age": 37, "title": "VP of Product & Executive Director", "yearBorn": 1988, "fiscalYear": 2024, "totalPay": 303350, "exercisedValue": 0, "unexercisedValue": 0}, {"maxAge": 1, "name": "Ms. Wenbei  Wang", "title": "VP, Deputy CFO and Head of Investor Relations & Capital Markets", "fiscalYear": 2024, "exercisedValue": 0, "unexercisedValue": 0}, {"maxAge": 1, "name": "Ms. Yang  Mu", "age": 45, "title": "VP of Human Resources & Executive Director", "yearBorn": 1980, "fiscalYear": 2024, "exercisedValue": 0, "unexercisedValue": 0}, {"maxAge": 1, "name": "Mr. Wing Yat  Lui", "age": 35, "title": "Joint Company Secretary", "yearBorn": 1990, "fiscalYear": 2024, "exercisedValue": 0, "unexercisedValue": 0}, {"maxAge": 1, "name": "Ms. Huaiyuan  Liang", "title": "Joint Company Secretary", "fiscalYear": 2024, "exercisedValue": 0, "unexercisedValue": 0}], "compensationAsOfEpochDate": 1735603200, "executiveTeam": [], "maxAge": 86400, "priceHint": 2, "previousClose": 13.8, "open": 13.56, "dayLow": 13.48, "dayHigh": 13.93, "regularMarketPreviousClose": 13.8, "regularMarketOpen": 13.56, "regularMarketDayLow": 13.48, "regularMarketDayHigh": 13.93, "dividendRate": 0.17, "dividendYield": 1.22, "exDividendDate": 1759881600, "payoutRatio": 0.1664, "beta": 0.485, "trailingPE": 12.971699, "forwardPE": 9.454692, "volume": 6139110, "regularMarketVolume": 6139110, "averageVolume": 4352890, "averageVolume10days": 4523580, "averageDailyVolume10Day": 4523580, "bid": 9.88, "ask": 17.03, "bidSize": 2, "askSize": 2, "marketCap": 6232226304, "nonDilutedMarketCap": 6129026832, "fiftyTwoWeekLow": 12.85, "fiftyTwoWeekHigh": 25.26, "allTimeHigh": 44.96, "allTimeLow": 9.745, "priceToSalesTrailing12Months": 0.7407823, "fiftyDayAverage": 13.7668, "twoHundredDayAverage": 19.036776, "trailingAnnualDividendRate": 0.0, "trailingAnnualDividendYield": 0.0, "currency": "USD", "tradeable": false, "enterpriseValue": -7618889728, "profitMargins": 0.40103, "floatShares": 738462125, "sharesOutstanding": 389989620, "sharesShort": 17928558, "sharesShortPriorMonth": 16359146, "sharesShortPreviousMonthDate": 1774915200, "dateShortInterest": 1777507200, "sharesPercentSharesOut": 0.039300002, "heldPercentInsiders": 0.0, "heldPercentInstitutions": 0.81086, "shortRatio": 4.79, "shortPercentOfFloat": 0.046, "impliedSharesOutstanding": 453252820, "bookValue": 6.5101166, "priceToBook": 2.1120973, "lastFiscalYearEnd": 1767139200, "nextFiscalYearEnd": 1798675200, "mostRecentQuarter": 1774915200, "earningsQuarterlyGrowth": 1.232, "netIncomeToCommon": 3373899008, "trailingEps": 1.06, "forwardEps": 1.4543043, "pegRatio": 0.18, "enterpriseToRevenue": -0.906, "enterpriseToEbitda": -2.26, "52WeekChange": -0.21786124, "SandP52WeekChange": 0.26208222, "lastDividendValue": 0.168, "lastDividendDate": 1759881600, "quoteType": "EQUITY", "currentPrice": 13.75, "targetHighPrice": 29.505886, "targetLowPrice": 15.7175455, "targetMeanPrice": 21.194471, "targetMedianPrice": 21.02355, "recommendationMean": 1.36364, "recommendationKey": "strong_buy", "numberOfAnalystOpinions": 21, "totalCash": 20497782784, "totalCashPerShare": 22.096, "ebitda": 3371167744, "totalDebt": 123596000, "quickRatio": 4.237, "currentRatio": 4.328, "totalRevenue": 8413032960, "debtToEquity": 0.602, "revenuePerShare": 18.385, "returnOnAssets": 0.076570004, "returnOnEquity": 0.18156, "grossProfits": 7190472192, "freeCashflow": 4053984256, "operatingCashflow": 4739364864, "earningsGrowth": 1.103, "revenueGrowth": 0.076, "grossMargins": 0.85468, "ebitdaMargins": 0.40071, "operatingMargins": 0.30145, "financialCurrency": "CNY", "symbol": "BZ", "language": "en-US", "region": "US", "typeDisp": "Equity", "quoteSourceName": "Nasdaq Real Time Price", "triggerable": true, "customPriceAlertConfidence": "HIGH", "corporateActions": [], "postMarketTime": 1779485787, "regularMarketTime": 1779480001, "exchange": "NMS", "messageBoardId": "finmb_715953746", "exchangeTimezoneName": "America/New_York", "exchangeTimezoneShortName": "EDT", "gmtOffSetMilliseconds": -14400000, "market": "us_market", "esgPopulated": false, "regularMarketChangePercent": -0.36232, "regularMarketPrice": 13.75, "marketState": "CLOSED", "shortName": "KANZHUN LIMITED - American Depo", "hasPrePostMarketData": true, "firstTradeDateMilliseconds": 1623418200000, "postMarketChangePercent": 0.0, "postMarketPrice": 13.75, "postMarketChange": 0.0, "regularMarketChange": -0.0500002, "regularMarketDayRange": "13.48 - 13.93", "fullExchangeName": "NasdaqGS", "averageDailyVolume3Month": 4352890, "fiftyTwoWeekLowChange": 0.8999996, "fiftyTwoWeekLowChangePercent": 0.07003888, "fiftyTwoWeekRange": "12.85 - 25.26", "fiftyTwoWeekHighChange": -11.51, "fiftyTwoWeekHighChangePercent": -0.45566112, "fiftyTwoWeekChangePercent": -21.786123, "dividendDate": 1761177600, "earningsTimestamp": 1779280200, "earningsTimestampStart": 1787142600, "earningsTimestampEnd": 1787142600, "earningsCallTimestampStart": 1779278400, "earningsCallTimestampEnd": 1779278400, "isEarningsDateEstimate": true, "epsTrailingTwelveMonths": 1.06, "epsForward": 1.4543043, "epsCurrentYear": 8.7444, "priceEpsCurrentYear": 1.5724349, "fiftyDayAverageChange": -0.016799927, "fiftyDayAverageChangePercent": -0.0012203219, "twoHundredDayAverageChange": -5.2867756, "twoHundredDayAverageChangePercent": -0.2777138, "sourceInterval": 15, "exchangeDataDelayedBy": 0, "averageAnalystRating": "1.4 - Strong Buy", "cryptoTradeable": false, "displayName": "Kanzhun", "trailingPegRatio": 0.1767, "__fetch_time": "2026-05-23"}]