[{"address1": "120 Tredegar Street", "city": "Richmond", "state": "VA", "zip": "23219", "country": "United States", "phone": "804 819 2284", "website": "https://www.dominionenergy.com", "industry": "Utilities - Regulated Electric", "industryKey": "utilities-regulated-electric", "industryDisp": "Utilities - Regulated Electric", "sector": "Utilities", "sectorKey": "utilities", "sectorDisp": "Utilities", "longBusinessSummary": "Dominion Energy, Inc. produces and distributes energy in the United States. It operates through three operating segments: Dominion Energy Virginia, Dominion Energy South Carolina, and Contracted Energy. The Dominion Energy Virginia segment generates, transmits, and distributes regulated electricity to approximately 2.8 million residential, commercial, industrial, and governmental customers in Virginia and North Carolina. The Dominion Energy South Carolina segment generates, transmits, and distributes electricity to approximately 0.8 million customers in the central, southern, and southwestern portions of South Carolina; and distributes natural gas to approximately 0.4 million residential, commercial, and industrial customers in South Carolina. The Contracted Energy segment is involved in the nonregulated long-term contracted renewable electric generation and renewable natural gas facility. As of December 31, 2023, the company's portfolio of assets included approximately 29.5 gigawatt of electric generating capacity; 10,600 miles of electric transmission lines; 79,300 miles of electric distribution lines; and 94,800 miles of gas distribution mains and related service facilities. The company was formerly known as Dominion Resources, Inc. Dominion Energy, Inc. was incorporated in 1983 and is headquartered in Richmond, Virginia.", "companyOfficers": [{"maxAge": 1, "name": "Mr. Robert M. Blue", "age": 56, "title": "President, CEO & Chairman of the Board", "yearBorn": 1968, "fiscalYear": 2023, "totalPay": 2943712, "exercisedValue": 0, "unexercisedValue": 0}, {"maxAge": 1, "name": "Mr. Steven D. Ridge", "age": 43, "title": "Executive VP & CFO", "yearBorn": 1981, "fiscalYear": 2023, "totalPay": 1283243, "exercisedValue": 0, "unexercisedValue": 0}, {"maxAge": 1, "name": "Ms. Diane G. Leopold", "age": 57, "title": "Executive VP & Chief Operating Officer", "yearBorn": 1967, "fiscalYear": 2023, "totalPay": 2348160, "exercisedValue": 0, "unexercisedValue": 0}, {"maxAge": 1, "name": "Mr. Carlos M. Brown", "age": 49, "title": "President of Dominion Energy Services, Executive VP, Chief Legal Officer & Corporate Secretary", "yearBorn": 1975, "fiscalYear": 2023, "totalPay": 1118535, "exercisedValue": 0, "unexercisedValue": 0}, {"maxAge": 1, "name": "Mr. Edward H. Baine", "age": 49, "title": "President of Utility Operations & Dominion Energy Virginia", "yearBorn": 1975, "fiscalYear": 2023, "totalPay": 1052838, "exercisedValue": 0, "unexercisedValue": 0}, {"maxAge": 1, "name": "Ms. Michele L. Cardiff", "age": 56, "title": "Senior VP, Controller & Chief Accounting Officer", "yearBorn": 1968, "fiscalYear": 2023, "exercisedValue": 0, "unexercisedValue": 0}, {"maxAge": 1, "name": "Mr. David  McFarland", "title": "Vice President of Investor Relations", "fiscalYear": 2023, "exercisedValue": 0, "unexercisedValue": 0}, {"maxAge": 1, "name": "Mr. William L. Murray", "age": 55, "title": "Senior Vice President of Corporate Affairs & Communications", "yearBorn": 1969, "fiscalYear": 2023, "exercisedValue": 0, "unexercisedValue": 0}, {"maxAge": 1, "name": "Ms. Regina J. Elbert", "title": "Senior VP & Chief Human Resources Officer", "fiscalYear": 2023, "exercisedValue": 0, "unexercisedValue": 0}, {"maxAge": 1, "name": "Mr. Daniel A. Weekley", "title": "President of Ohio Operations", "fiscalYear": 2023, "exercisedValue": 0, "unexercisedValue": 0}], "auditRisk": 3, "boardRisk": 5, "compensationRisk": 1, "shareHolderRightsRisk": 6, "overallRisk": 3, "governanceEpochDate": 1738368000, "compensationAsOfEpochDate": 1703980800, "irWebsite": "https://www.dom.com/investors/index.jsp", "maxAge": 86400, "priceHint": 2, "previousClose": 56.71, "open": 56.92, "dayLow": 55.45, "dayHigh": 56.97, "regularMarketPreviousClose": 56.71, "regularMarketOpen": 56.92, "regularMarketDayLow": 55.45, "regularMarketDayHigh": 56.97, "dividendRate": 2.67, "dividendYield": 0.048, "exDividendDate": 1740700800, "payoutRatio": 1.2136, "fiveYearAvgDividendYield": 4.48, "beta": 0.606, "trailingPE": 25.26818, "forwardPE": 15.460305, "volume": 3613277, "regularMarketVolume": 3613277, "averageVolume": 4530478, "averageVolume10days": 4992400, "averageDailyVolume10Day": 4992400, "bid": 55.56, "ask": 56.22, "bidSize": 800, "askSize": 900, "marketCap": 46696157184, "fiftyTwoWeekLow": 44.17, "fiftyTwoWeekHigh": 61.97, "priceToSalesTrailing12Months": 3.2295566, "fiftyDayAverage": 54.5922, "twoHundredDayAverage": 54.8177, "trailingAnnualDividendRate": 2.67, "trailingAnnualDividendYield": 0.047081646, "currency": "USD", "enterpriseValue": 89313132544, "profitMargins": 0.1469, "floatShares": 838220405, "sharesOutstanding": 840009984, "sharesShort": 18498722, "sharesShortPriorMonth": 14179140, "sharesShortPreviousMonthDate": 1735603200, "dateShortInterest": 1738281600, "sharesPercentSharesOut": 0.022, "heldPercentInsiders": 0.0028799998, "heldPercentInstitutions": 0.78299004, "shortRatio": 4.23, "shortPercentOfFloat": 0.022, "impliedSharesOutstanding": 856934016, "bookValue": 31.17, "priceToBook": 1.7834456, "lastFiscalYearEnd": 1735603200, "nextFiscalYearEnd": 1767139200, "mostRecentQuarter": 1735603200, "earningsQuarterlyGrowth": -0.383, "netIncomeToCommon": 1927000064, "trailingEps": 2.2, "forwardEps": 3.38, "lastSplitFactor": "2:1", "lastSplitDate": 1195516800, "enterpriseToRevenue": 6.177, "enterpriseToEbitda": 14.496, "52WeekChange": 0.22579932, "SandP52WeekChange": 0.22894537, "lastDividendValue": 0.668, "lastDividendDate": 1732838400, "exchange": "NYQ", "quoteType": "EQUITY", "symbol": "D", "underlyingSymbol": "D", "shortName": "Dominion Energy, Inc.", "longName": "Dominion Energy, Inc.", "firstTradeDateEpochUtc": 322151400, "timeZoneFullName": "America/New_York", "timeZoneShortName": "EST", "uuid": "f623e75a-f30e-32bb-973d-6df5b50bb7b5", "messageBoardId": "finmb_267105", "gmtOffSetMilliseconds": -18000000, "currentPrice": 55.59, "targetHighPrice": 66.0, "targetLowPrice": 50.73, "targetMeanPrice": 58.48312, "targetMedianPrice": 59.0, "recommendationMean": 2.73684, "recommendationKey": "hold", "numberOfAnalystOpinions": 16, "totalCash": 1776000000, "totalCashPerShare": 2.114, "ebitda": 6161332736, "totalDebt": 43044999168, "totalRevenue": 14458999808, "debtToEquity": 156.351, "revenuePerShare": 17.225, "returnOnEquity": 0.06807, "grossProfits": 6552000000, "earningsGrowth": -0.417, "revenueGrowth": -0.038, "grossMargins": 0.45314, "ebitdaMargins": 0.42611998, "operatingMargins": 0.18235001, "financialCurrency": "USD", "trailingPegRatio": 1.9464, "__fetch_time": "2025-02-15"}]