[{"address1": "225 Broadhollow Road", "address2": "Suite 307", "city": "Melville", "state": "NY", "zip": "11747", "country": "United States", "phone": "212 564 4922", "website": "https://www.dtst.com", "industry": "Information Technology Services", "industryKey": "information-technology-services", "industryDisp": "Information Technology Services", "sector": "Technology", "sectorKey": "technology", "sectorDisp": "Technology", "longBusinessSummary": "Data Storage Corporation provides enterprise cloud and business continuity solutions in the United States and internationally. The company operates through three segments: CloudFirst, CloudFirst Europe, and Nexxis. It offers fully managed cloud hosting services for IBM Power systems, such as IBM i and AIX, as well as x86 environments; cloud solutions, including migration services to ensure seamless transfer of data and applications from legacy systems to the cloud with minimal downtime; and delivers robust disaster-recovery-as-a-service and business continuity solutions to protect organizations from downtime and data loss. The company's recovery services provide off-site data replication, rapid failover for IBM i/AIX and Windows/Linux systems, and cloud-based backup services that ensure clients can restore critical applications in the event of cyberattacks, hardware failures, or natural disasters for minimizing operational disruption. It also offers cybersecurity solutions comprising cybersecurity and compliance services consist of endpoint protection, network security, data encryption, ransomware defense, vulnerability assessments, and IBM i security monitoring. In addition, the company provides managed IT services and support services, such as cloud offerings with managed services comprising systems monitoring, IT automation, and voice and data communications solutions; and voice over Internet protocol/unified communications and dedicated internet connectivity solutions. Further, it offers delivers fully managed cloud-based voice over internet services, data transport, internet access, and SD-WAN solutions focused on business continuity for modern business environment. Data Storage Corporation was founded in 2001 and is headquartered in Melville, New York.", "fullTimeEmployees": 53, "companyOfficers": [{"maxAge": 1, "name": "Mr. Charles M. Piluso", "age": 72, "title": "Chairman of the Board & CEO", "yearBorn": 1953, "fiscalYear": 2024, "totalPay": 467298, "exercisedValue": 0, "unexercisedValue": 45418}], "compensationAsOfEpochDate": 1735603200, "executiveTeam": [], "maxAge": 86400, "priceHint": 4, "previousClose": 4.35, "open": 4.3961, "dayLow": 4.2648, "dayHigh": 4.3961, "regularMarketPreviousClose": 4.35, "regularMarketOpen": 4.3961, "regularMarketDayLow": 4.2648, "regularMarketDayHigh": 4.3961, "payoutRatio": 0.0, "beta": 1.085, "trailingPE": 23.833332, "forwardPE": -11.0, "volume": 6107, "regularMarketVolume": 6107, "averageVolume": 68635, "averageVolume10days": 15420, "averageDailyVolume10Day": 15420, "bid": 3.06, "ask": 5.52, "bidSize": 2, "askSize": 2, "marketCap": 32167956, "fiftyTwoWeekLow": 2.93, "fiftyTwoWeekHigh": 5.44, "allTimeHigh": 13.1, "allTimeLow": 0.02, "priceToSalesTrailing12Months": 1.260015, "fiftyDayAverage": 4.7534, "twoHundredDayAverage": 4.31055, "trailingAnnualDividendRate": 0.0, "trailingAnnualDividendYield": 0.0, "currency": "USD", "tradeable": false, "enterpriseValue": -13833102, "profitMargins": 0.64071, "floatShares": 5478225, "sharesOutstanding": 2167138, "sharesShort": 38636, "sharesShortPriorMonth": 54427, "sharesShortPreviousMonthDate": 1767139200, "dateShortInterest": 1769731200, "sharesPercentSharesOut": 0.0178, "heldPercentInsiders": 0.78235, "heldPercentInstitutions": 0.57756, "shortRatio": 1.2, "shortPercentOfFloat": 0.0087, "impliedSharesOutstanding": 7498358, "bookValue": 5.292, "priceToBook": 0.8106576, "lastFiscalYearEnd": 1735603200, "nextFiscalYearEnd": 1767139200, "mostRecentQuarter": 1759190400, "earningsQuarterlyGrowth": 136.081, "netIncomeToCommon": 1210255, "trailingEps": 0.18, "forwardEps": -0.39, "enterpriseToRevenue": -0.542, "enterpriseToEbitda": -12.157, "52WeekChange": 0.100000024, "SandP52WeekChange": 0.11527538, "quoteType": "EQUITY", "currentPrice": 4.29, "recommendationKey": "none", "totalCash": 45756692, "totalCashPerShare": 6.102, "ebitda": 1137888, "totalDebt": 0, "quickRatio": 5.625, "currentRatio": 5.64, "totalRevenue": 25529820, "revenuePerShare": 3.583, "returnOnAssets": -0.0037, "returnOnEquity": 0.04061, "grossProfits": 11186374, "freeCashflow": 7328416, "operatingCashflow": 631676, "earningsGrowth": 274.596, "revenueGrowth": 0.282, "grossMargins": 0.43817002, "ebitdaMargins": 0.04457, "operatingMargins": -2.6345098, "financialCurrency": "USD", "symbol": "DTST", "language": "en-US", "region": "US", "typeDisp": "Equity", "quoteSourceName": "Nasdaq Real Time Price", "triggerable": true, "customPriceAlertConfidence": "HIGH", "fiftyDayAverageChange": -0.4633999, "fiftyDayAverageChangePercent": -0.09748809, "twoHundredDayAverageChange": -0.020550251, "twoHundredDayAverageChangePercent": -0.004767431, "sourceInterval": 15, "exchangeDataDelayedBy": 0, "ipoExpectedDate": "2021-05-14", "cryptoTradeable": false, "exchange": "NCM", "messageBoardId": "finmb_7853869", "exchangeTimezoneName": "America/New_York", "exchangeTimezoneShortName": "EST", "gmtOffSetMilliseconds": -18000000, "market": "us_market", "esgPopulated": false, "marketState": "CLOSED", "shortName": "Data Storage Corporation", "longName": "Data Storage Corporation", "corporateActions": [], "postMarketTime": 1771634252, "regularMarketTime": 1771621200, "regularMarketChangePercent": -1.379309, "regularMarketPrice": 4.29, "postMarketChangePercent": 1.1655056, "postMarketPrice": 4.34, "postMarketChange": 0.05000019, "regularMarketChange": -0.059999943, "regularMarketDayRange": "4.2648 - 4.3961", "fullExchangeName": "NasdaqCM", "averageDailyVolume3Month": 68635, "fiftyTwoWeekLowChange": 1.3599999, "fiftyTwoWeekLowChangePercent": 0.46416378, "fiftyTwoWeekRange": "2.93 - 5.44", "fiftyTwoWeekHighChange": -1.1500001, "fiftyTwoWeekHighChangePercent": -0.21139707, "fiftyTwoWeekChangePercent": 10.000002, "earningsTimestampStart": 1774877400, "earningsTimestampEnd": 1774877400, "earningsCallTimestampStart": 1763564400, "earningsCallTimestampEnd": 1763564400, "isEarningsDateEstimate": true, "epsTrailingTwelveMonths": 0.18, "epsForward": -0.39, "epsCurrentYear": 2.06, "priceEpsCurrentYear": 2.0825243, "hasPrePostMarketData": true, "firstTradeDateMilliseconds": 1331731800000, "displayName": "Data Storage", "trailingPegRatio": null, "__fetch_time": "2026-02-21"}]