[{"address1": "625 Howe Street", "address2": "Suite 580", "city": "Vancouver", "state": "BC", "zip": "V6C 2T6", "country": "Canada", "phone": "604-687-3959", "fax": "604-687-1448", "website": "https://www.ingold.ca", "industry": "Gold", "sector": "Basic Materials", "longBusinessSummary": "Independence Gold Corp. engages in the acquisition, exploration, and evaluation of precious metal properties in Canada and North America. It explores for gold and silver deposits. The company holds 100% interest in the 3Ts Project comprising six claim groups and consist of seventy mineral claims covering an approximately 8,840 hectares located in the Nechako Plateau region of central British Columbia; and the Laidman Project comprising six mineral tenures covering an approximately 10,800 hectares located in the British Columbia. Independence Gold Corp. was incorporated in 2011 and is headquartered in Vancouver, Canada.", "companyOfficers": [{"maxAge": 1, "name": "Mr. Randy Christopher Turner B.Sc., P.Geo.", "age": 74, "title": "President, CEO & Chairman", "yearBorn": 1949, "fiscalYear": 2022, "totalPay": 151674, "exercisedValue": 0, "unexercisedValue": 0}, {"maxAge": 1, "name": "Mr. Harry  Chan CPA, CGA, CPA", "title": "CFO & Corporate Secretary", "fiscalYear": 2022, "totalPay": 52417, "exercisedValue": 0, "unexercisedValue": 0}, {"maxAge": 1, "name": "Mr. David James Pawliuk B.Sc., P.Geo", "title": "Advisor", "fiscalYear": 2022, "exercisedValue": 0, "unexercisedValue": 0}], "compensationAsOfEpochDate": 1672444800, "maxAge": 86400, "priceHint": 4, "previousClose": 0.146, "open": 0.1358, "dayLow": 0.1358, "dayHigh": 0.1461, "regularMarketPreviousClose": 0.146, "regularMarketOpen": 0.1358, "regularMarketDayLow": 0.1358, "regularMarketDayHigh": 0.1461, "beta": 1.5, "volume": 60500, "regularMarketVolume": 60500, "averageVolume": 146481, "averageVolume10days": 160394, "averageDailyVolume10Day": 160394, "bid": 0.147, "ask": 0.1499, "marketCap": 24426528, "fiftyTwoWeekLow": 0.081, "fiftyTwoWeekHigh": 0.233, "fiftyDayAverage": 0.1574556, "twoHundredDayAverage": 0.15171215, "currency": "USD", "enterpriseValue": 21765840, "floatShares": 147741965, "sharesOutstanding": 167304992, "heldPercentInsiders": 0.13508001, "bookValue": 0.043, "priceToBook": 3.3953488, "lastFiscalYearEnd": 1703980800, "nextFiscalYearEnd": 1735603200, "mostRecentQuarter": 1711843200, "netIncomeToCommon": -3193309, "trailingEps": -0.02, "enterpriseToEbitda": -7.414, "exchange": "OQB", "quoteType": "EQUITY", "symbol": "IEGCF", "underlyingSymbol": "IEGCF", "shortName": "INDEPENDENCE GOLD CORP", "longName": "Independence Gold Corp.", "firstTradeDateEpochUtc": 1326810600, "timeZoneFullName": "America/New_York", "timeZoneShortName": "EDT", "uuid": "35411db6-0903-3760-a690-142a96054dcf", "gmtOffSetMilliseconds": -14400000, "currentPrice": 0.146, "recommendationKey": "none", "totalCash": 3146433, "totalCashPerShare": 0.019, "ebitda": -2935784, "totalDebt": 402100, "quickRatio": 5.526, "currentRatio": 5.656, "debtToEquity": 5.627, "returnOnAssets": -0.27224, "returnOnEquity": -0.53540003, "freeCashflow": -2016516, "operatingCashflow": -3312969, "financialCurrency": "CAD", "trailingPegRatio": null, "__fetch_time": "2024-06-18"}]