[{"address1": "1 De Haro Street", "city": "San Francisco", "state": "CA", "zip": "94107", "country": "United States", "phone": "415 985 2400", "website": "https://www.samsara.com", "industry": "Software - Infrastructure", "industryKey": "software-infrastructure", "industryDisp": "Software - Infrastructure", "sector": "Technology", "sectorKey": "technology", "sectorDisp": "Technology", "longBusinessSummary": "Samsara Inc. provides solutions to connect physical operations data to its connected operations platform in the United States and internationally. The company's Connected Operations Platform includes Data Platform, which ingests, aggregates, and enriches data from its IoT devices and a growing ecosystem of connected assets and third-party systems, and which has embedded capabilities for AI, workflows and analytics, alerts, API connections, and data security and privacy. Its applications include video-based safety that enables customers to build a safety program and protect their teams with AI-enabled video; vehicle telematics, which provides visibility into real-time vehicle location and diagnostics with GPS tracking, routing and dispatch, fuel management, driver recognition, electric vehicle usage and charge planning, preventative maintenance, and advanced insights to manage fuel and energy costs; and workforce apps that enhance safety and productivity for frontline workers and enable regulatory compliance, capture electronic documents, perform maintenance inspections, maintain compliance logs, complete safety audits and risk assessments, submit timesheets, and message with back-office administration. The company also provides equipment monitoring, which offers visibility and management of unpowered and powered assets, including generators, compressors, and heavy construction equipment and trailers to prevent unplanned downtime and avoid critical safety and compliance issues; and site visibility that provides remote visibility into sites to enhance onsite security, safety, and incident response times. It serves transportation, construction, wholesale and retail trade, field services, logistics, manufacturing, utilities and energy, government, healthcare and education, food and beverage, and other industries. The company was incorporated in 2015 and is headquartered in San Francisco, California.", "fullTimeEmployees": 3500, "companyOfficers": [{"maxAge": 1, "name": "Mr. Sanjit  Biswas", "age": 43, "title": "Co-Founder, CEO & Chairman", "yearBorn": 1982, "fiscalYear": 2025, "totalPay": 95207, "exercisedValue": 0, "unexercisedValue": 0}, {"maxAge": 1, "name": "Mr. John  Bicket", "age": 45, "title": "Co-Founder, Executive VP, CTO & Director", "yearBorn": 1980, "fiscalYear": 2025, "totalPay": 96696, "exercisedValue": 0, "unexercisedValue": 0}, {"maxAge": 1, "name": "Mr. Dominic  Phillips", "age": 43, "title": "Executive VP & CFO", "yearBorn": 1982, "fiscalYear": 2025, "totalPay": 951232, "exercisedValue": 0, "unexercisedValue": 0}, {"maxAge": 1, "name": "Mr. Adam  Eltoukhy J.D.", "age": 41, "title": "Executive VP, Chief Legal Officer & Corporate Secretary", "yearBorn": 1984, "fiscalYear": 2025, "totalPay": 647437, "exercisedValue": 0, "unexercisedValue": 0}, {"maxAge": 1, "name": "Mr. Ben  Kirchhoff", "title": "Chief Accounting Officer", "fiscalYear": 2025, "exercisedValue": 0, "unexercisedValue": 0}, {"maxAge": 1, "name": "Mr. Stephen  Franchetti", "title": "Chief Information Officer", "fiscalYear": 2025, "exercisedValue": 0, "unexercisedValue": 0}, {"maxAge": 1, "name": "Mr. Mike  Chang", "title": "Vice President of Corporate Development & Investor Relations", "fiscalYear": 2025, "exercisedValue": 0, "unexercisedValue": 0}, {"maxAge": 1, "name": "Ms. Meagen  Eisenberg", "age": 50, "title": "Chief Marketing Officer", "yearBorn": 1975, "fiscalYear": 2025, "exercisedValue": 0, "unexercisedValue": 0}, {"maxAge": 1, "name": "Mr. Steve  Pickle", "title": "Chief People Officer", "fiscalYear": 2025, "exercisedValue": 0, "unexercisedValue": 0}, {"maxAge": 1, "name": "Mr. Kiren  Sekar", "age": 44, "title": "Executive VP & Chief Product Officer", "yearBorn": 1981, "fiscalYear": 2025, "totalPay": 609327, "exercisedValue": 0, "unexercisedValue": 9120007}], "auditRisk": 1, "boardRisk": 7, "compensationRisk": 9, "shareHolderRightsRisk": 10, "overallRisk": 9, "governanceEpochDate": 1768176000, "compensationAsOfEpochDate": 1767139200, "executiveTeam": [], "maxAge": 86400, "priceHint": 2, "previousClose": 34.26, "open": 34.23, "dayLow": 34.11, "dayHigh": 35.86, "regularMarketPreviousClose": 34.26, "regularMarketOpen": 34.23, "regularMarketDayLow": 34.11, "regularMarketDayHigh": 35.86, "payoutRatio": 0.0, "beta": 1.618, "forwardPE": 59.663464, "volume": 6819589, "regularMarketVolume": 6819589, "averageVolume": 5276621, "averageVolume10days": 6968730, "averageDailyVolume10Day": 6968730, "bid": 34.55, "ask": 34.75, "bidSize": 900, "askSize": 400, "marketCap": 20131670016, "fiftyTwoWeekLow": 31.4, "fiftyTwoWeekHigh": 61.9, "allTimeHigh": 61.9, "allTimeLow": 8.42, "priceToSalesTrailing12Months": 13.239041, "fiftyDayAverage": 37.8012, "twoHundredDayAverage": 38.79415, "trailingAnnualDividendRate": 0.0, "trailingAnnualDividendYield": 0.0, "currency": "USD", "tradeable": false, "enterpriseValue": 19445473280, "profitMargins": -0.02785, "floatShares": 341707573, "sharesOutstanding": 358191765, "sharesShort": 23510135, "sharesShortPriorMonth": 23888709, "sharesShortPreviousMonthDate": 1764288000, "dateShortInterest": 1767139200, "sharesPercentSharesOut": 0.040700004, "heldPercentInsiders": 0.03987, "heldPercentInstitutions": 0.90318, "shortRatio": 3.61, "shortPercentOfFloat": 0.0749, "impliedSharesOutstanding": 577004057, "bookValue": 2.259, "priceToBook": 15.444886, "lastFiscalYearEnd": 1738368000, "nextFiscalYearEnd": 1769904000, "mostRecentQuarter": 1761955200, "netIncomeToCommon": -42357000, "trailingEps": -0.07, "forwardEps": 0.58478, "enterpriseToRevenue": 12.788, "enterpriseToEbitda": -278.118, "52WeekChange": -0.27445996, "SandP52WeekChange": 0.14799047, "quoteType": "EQUITY", "currentPrice": 34.89, "targetHighPrice": 60.0, "targetLowPrice": 39.0, "targetMeanPrice": 50.18, "targetMedianPrice": 50.0, "recommendationMean": 1.59091, "recommendationKey": "buy", "numberOfAnalystOpinions": 20, "totalCash": 761836032, "totalCashPerShare": 1.32, "ebitda": -69918000, "totalDebt": 75637000, "quickRatio": 1.271, "currentRatio": 1.56, "totalRevenue": 1520628992, "debtToEquity": 5.803, "revenuePerShare": 2.669, "returnOnAssets": -0.023559999, "returnOnEquity": -0.03679, "grossProfits": 1170690944, "freeCashflow": 282176736, "operatingCashflow": 220336000, "revenueGrowth": 0.292, "grossMargins": 0.76987, "ebitdaMargins": -0.04598, "operatingMargins": -0.00414, "financialCurrency": "USD", "symbol": "IOT", "language": "en-US", "region": "US", "typeDisp": "Equity", "quoteSourceName": "Nasdaq Real Time Price", "triggerable": true, "customPriceAlertConfidence": "HIGH", "epsTrailingTwelveMonths": -0.07, "epsForward": 0.58478, "epsCurrentYear": 0.50356, "priceEpsCurrentYear": 69.286674, "fiftyDayAverageChange": -2.9112015, "fiftyDayAverageChangePercent": -0.07701346, "twoHundredDayAverageChange": -3.904152, "twoHundredDayAverageChangePercent": -0.100637645, "sourceInterval": 15, "exchangeDataDelayedBy": 0, "ipoExpectedDate": "2021-12-15", "averageAnalystRating": "1.6 - Buy", "cryptoTradeable": false, "regularMarketChangePercent": 1.83888, "regularMarketPrice": 34.89, "hasPrePostMarketData": true, "firstTradeDateMilliseconds": 1639578600000, "postMarketChangePercent": 0.02866763, "postMarketPrice": 34.9, "postMarketChange": 0.010002136, "regularMarketChange": 0.630001, "regularMarketDayRange": "34.11 - 35.86", "fullExchangeName": "NYSE", "averageDailyVolume3Month": 5276621, "fiftyTwoWeekLowChange": 3.4899998, "fiftyTwoWeekLowChangePercent": 0.11114649, "fiftyTwoWeekRange": "31.4 - 61.9", "fiftyTwoWeekHighChange": -27.010002, "fiftyTwoWeekHighChangePercent": -0.43634897, "fiftyTwoWeekChangePercent": -27.445995, "earningsTimestamp": 1764882000, "earningsTimestampStart": 1764882000, "earningsTimestampEnd": 1764882000, "earningsCallTimestampStart": 1764885600, "earningsCallTimestampEnd": 1764885600, "isEarningsDateEstimate": false, "corporateActions": [], "postMarketTime": 1768611583, "regularMarketTime": 1768597202, "exchange": "NYQ", "messageBoardId": "finmb_301743802", "exchangeTimezoneName": "America/New_York", "exchangeTimezoneShortName": "EST", "gmtOffSetMilliseconds": -18000000, "market": "us_market", "esgPopulated": false, "marketState": "CLOSED", "shortName": "Samsara Inc.", "longName": "Samsara Inc.", "displayName": "Samsara", "trailingPegRatio": null, "__fetch_time": "2026-01-17"}]