[{"address1": "120 Wood Road", "city": "Kingston", "state": "NY", "zip": "12401", "country": "United States", "phone": "845 802 7900", "website": "https://www.kingstonecompanies.com", "industry": "Insurance - Property & Casualty", "industryKey": "insurance-property-casualty", "industryDisp": "Insurance - Property & Casualty", "sector": "Financial Services", "sectorKey": "financial-services", "sectorDisp": "Financial Services", "longBusinessSummary": "Kingstone Companies, Inc., through its subsidiary, Kingstone Insurance Company (\"KICO\"), provides property and casualty insurance products in the United States. It offers personal line of insurance products, such as homeowners, dwelling fire, cooperative/condominiums, renters, and personal umbrella policies; and commercial auto insurance products. It also provides for-hire vehicle physical damage only policies for livery and car service vehicles and taxicabs; and canine legal liability policies. In addition, the company offers reinsurance products. It underwrites its products through retail and wholesale agents and brokers. The company was formerly known as DCAP Group, Inc. and changed its name to Kingstone Companies, Inc. in July 2009. Kingstone Companies, Inc. was founded in 1886 and is headquartered in Kingston, New York.", "fullTimeEmployees": 99, "companyOfficers": [{"maxAge": 1, "name": "Ms. Meryl S. Golden", "age": 65, "title": "President, CEO & Director", "yearBorn": 1960, "fiscalYear": 2024, "totalPay": 1022158, "exercisedValue": 0, "unexercisedValue": 0}, {"maxAge": 1, "name": "Ms. Sarah  Chen", "age": 42, "title": "Chief Actuary & SVP and Head of Product Management of Kingstone Insurance Company", "yearBorn": 1983, "fiscalYear": 2024, "totalPay": 529585, "exercisedValue": 0, "unexercisedValue": 0}, {"maxAge": 1, "name": "Mr. Floyd R. Tupper CPA", "age": 70, "title": "Secretary & Independent Director", "yearBorn": 1955, "fiscalYear": 2024, "totalPay": 75000, "exercisedValue": 0, "unexercisedValue": 0}, {"maxAge": 1, "name": "Mr. Randy L. Patten", "title": "Chief Financial Officer", "fiscalYear": 2024, "exercisedValue": 0, "unexercisedValue": 0}, {"maxAge": 1, "name": "Mr. Victor Jay Brodsky CPA", "age": 67, "title": "Chief Accounting Officer", "yearBorn": 1958, "fiscalYear": 2024, "totalPay": 549244, "exercisedValue": 0, "unexercisedValue": 0}, {"maxAge": 1, "name": "Mr. David  Fernandez", "title": "Senior VP & Chief Claims Officer", "fiscalYear": 2024, "exercisedValue": 0, "unexercisedValue": 0}], "auditRisk": 8, "boardRisk": 3, "compensationRisk": 7, "shareHolderRightsRisk": 3, "overallRisk": 4, "governanceEpochDate": 1768176000, "compensationAsOfEpochDate": 1735603200, "irWebsite": "http://www.kingstonecompanies.com/investor_information.asp", "executiveTeam": [], "maxAge": 86400, "priceHint": 2, "previousClose": 15.91, "open": 15.87, "dayLow": 15.4452, "dayHigh": 15.8933, "regularMarketPreviousClose": 15.91, "regularMarketOpen": 15.87, "regularMarketDayLow": 15.4452, "regularMarketDayHigh": 15.8933, "dividendRate": 0.1, "dividendYield": 0.64, "exDividendDate": 1762819200, "payoutRatio": 0.0222, "fiveYearAvgDividendYield": 4.24, "beta": 0.43, "trailingPE": 6.9511113, "forwardPE": 6.5166664, "volume": 196316, "regularMarketVolume": 196316, "averageVolume": 139073, "averageVolume10days": 150290, "averageDailyVolume10Day": 150290, "bid": 11.26, "ask": 19.85, "bidSize": 2, "askSize": 2, "marketCap": 221265776, "fiftyTwoWeekLow": 13.08, "fiftyTwoWeekHigh": 22.4, "allTimeHigh": 22.4, "allTimeLow": 0.04, "priceToSalesTrailing12Months": 1.1142224, "fiftyDayAverage": 15.7338, "twoHundredDayAverage": 15.533875, "trailingAnnualDividendRate": 0.05, "trailingAnnualDividendYield": 0.0031426777, "currency": "USD", "tradeable": false, "enterpriseValue": 199400576, "profitMargins": 0.15835, "floatShares": 11392782, "sharesOutstanding": 14147428, "sharesShort": 533840, "sharesShortPriorMonth": 635642, "sharesShortPreviousMonthDate": 1764288000, "dateShortInterest": 1767139200, "sharesPercentSharesOut": 0.0377, "heldPercentInsiders": 0.22888, "heldPercentInstitutions": 0.53595, "shortRatio": 4.04, "shortPercentOfFloat": 0.0397, "impliedSharesOutstanding": 14147428, "bookValue": 7.609, "priceToBook": 2.0554607, "lastFiscalYearEnd": 1735603200, "nextFiscalYearEnd": 1767139200, "mostRecentQuarter": 1759190400, "earningsQuarterlyGrowth": 0.558, "netIncomeToCommon": 31446142, "trailingEps": 2.25, "forwardEps": 2.4, "lastSplitFactor": "1:5", "lastSplitDate": 1093478400, "enterpriseToRevenue": 1.004, "enterpriseToEbitda": 4.901, "52WeekChange": -0.0050031543, "SandP52WeekChange": 0.14799047, "lastDividendValue": 0.05, "lastDividendDate": 1762732800, "quoteType": "EQUITY", "currentPrice": 15.64, "targetHighPrice": 22.0, "targetLowPrice": 22.0, "targetMeanPrice": 22.0, "targetMedianPrice": 22.0, "recommendationKey": "none", "numberOfAnalystOpinions": 1, "totalCash": 26772302, "totalCashPerShare": 1.892, "ebitda": 40684724, "totalDebt": 4907105, "quickRatio": 0.256, "currentRatio": 0.609, "totalRevenue": 198583136, "debtToEquity": 4.558, "revenuePerShare": 14.7, "returnOnAssets": 0.061550003, "returnOnEquity": 0.37587002, "grossProfits": 45170980, "freeCashflow": 49628936, "operatingCashflow": 76049736, "earningsGrowth": 0.345, "revenueGrowth": 0.365, "grossMargins": 0.22747, "ebitdaMargins": 0.20488001, "operatingMargins": 0.24759, "financialCurrency": "USD", "symbol": "KINS", "language": "en-US", "region": "US", "typeDisp": "Equity", "quoteSourceName": "Nasdaq Real Time Price", "triggerable": true, "customPriceAlertConfidence": "HIGH", "corporateActions": [], "postMarketTime": 1768597804, "regularMarketTime": 1768597202, "exchange": "NCM", "messageBoardId": "finmb_398246", "exchangeTimezoneName": "America/New_York", "exchangeTimezoneShortName": "EST", "gmtOffSetMilliseconds": -18000000, "market": "us_market", "esgPopulated": false, "priceEpsCurrentYear": 7.109091, "fiftyDayAverageChange": -0.09379959, "fiftyDayAverageChangePercent": -0.0059616617, "twoHundredDayAverageChange": 0.10612488, "twoHundredDayAverageChangePercent": 0.006831835, "sourceInterval": 15, "exchangeDataDelayedBy": 0, "cryptoTradeable": false, "hasPrePostMarketData": true, "firstTradeDateMilliseconds": 940944600000, "postMarketChangePercent": 0.0, "marketState": "CLOSED", "regularMarketChangePercent": -1.69704, "regularMarketPrice": 15.64, "postMarketPrice": 15.64, "postMarketChange": 0.0, "regularMarketChange": -0.27, "regularMarketDayRange": "15.4452 - 15.8933", "fullExchangeName": "NasdaqCM", "averageDailyVolume3Month": 139073, "fiftyTwoWeekLowChange": 2.5600004, "fiftyTwoWeekLowChangePercent": 0.19571869, "fiftyTwoWeekRange": "13.08 - 22.4", "fiftyTwoWeekHighChange": -6.7599993, "fiftyTwoWeekHighChangePercent": -0.30178568, "fiftyTwoWeekChangePercent": -0.5003154, "dividendDate": 1764115200, "earningsTimestamp": 1762462800, "earningsTimestampStart": 1762462800, "earningsTimestampEnd": 1762462800, "earningsCallTimestampStart": 1762522200, "earningsCallTimestampEnd": 1762522200, "isEarningsDateEstimate": false, "epsTrailingTwelveMonths": 2.25, "epsForward": 2.4, "epsCurrentYear": 2.2, "shortName": "Kingstone Companies, Inc", "longName": "Kingstone Companies, Inc.", "displayName": "Kingstone Companies", "trailingPegRatio": null, "__fetch_time": "2026-01-17"}]